stackit/loadbalancer/__init__.py
stackit/loadbalancer/api/__init__.py
stackit/loadbalancer/api/default_api.py
stackit/loadbalancer/api_client.py
stackit/loadbalancer/api_response.py
stackit/loadbalancer/configuration.py
stackit/loadbalancer/exceptions.py
stackit/loadbalancer/models/__init__.py
stackit/loadbalancer/models/active_health_check.py
stackit/loadbalancer/models/create_credentials_payload.py
stackit/loadbalancer/models/create_credentials_response.py
stackit/loadbalancer/models/create_load_balancer_payload.py
stackit/loadbalancer/models/credentials_response.py
stackit/loadbalancer/models/get_credentials_response.py
stackit/loadbalancer/models/get_quota_response.py
stackit/loadbalancer/models/google_protobuf_any.py
stackit/loadbalancer/models/list_credentials_response.py
stackit/loadbalancer/models/list_load_balancers_response.py
stackit/loadbalancer/models/list_plans_response.py
stackit/loadbalancer/models/listener.py
stackit/loadbalancer/models/load_balancer.py
stackit/loadbalancer/models/load_balancer_error.py
stackit/loadbalancer/models/load_balancer_options.py
stackit/loadbalancer/models/loadbalancer_option_access_control.py
stackit/loadbalancer/models/loadbalancer_option_logs.py
stackit/loadbalancer/models/loadbalancer_option_metrics.py
stackit/loadbalancer/models/loadbalancer_option_observability.py
stackit/loadbalancer/models/network.py
stackit/loadbalancer/models/options_tcp.py
stackit/loadbalancer/models/options_udp.py
stackit/loadbalancer/models/plan_details.py
stackit/loadbalancer/models/security_group.py
stackit/loadbalancer/models/server_name_indicator.py
stackit/loadbalancer/models/session_persistence.py
stackit/loadbalancer/models/status.py
stackit/loadbalancer/models/target.py
stackit/loadbalancer/models/target_pool.py
stackit/loadbalancer/models/update_credentials_payload.py
stackit/loadbalancer/models/update_credentials_response.py
stackit/loadbalancer/models/update_load_balancer_payload.py
stackit_loadbalancer-0.8.0.dist-info/METADATA
stackit_loadbalancer-0.8.0.dist-info/WHEEL
stackit_loadbalancer-0.8.0.dist-info/licenses/LICENSE.md
stackit_loadbalancer-0.8.0.dist-info/licenses/NOTICE.txt
stackit_loadbalancer-0.8.0.dist-info/RECORD
